prosto_sms/__init__.py
prosto_sms/exceptions.py
prosto_sms/methods.py
prosto_sms/models.py
prosto_sms-0.0.3.dist-info/METADATA
prosto_sms-0.0.3.dist-info/WHEEL
prosto_sms-0.0.3.dist-info/top_level.txt
prosto_sms-0.0.3.dist-info/RECORD
