Metadata-Version: 2.1
Name: prosto_sms
Version: 0.0.3
Summary: sms-prosto api wrapper written in python
Home-page: https://github.com/exituser/prosto-sms-python
Author: Alex Dennitsev
Author-email: me@chydo.dev
Classifier: Environment :: Web Environment
Classifier: Programming Language :: Python :: 3.9
Classifier: Programming Language :: Python :: 3.11
Requires-Dist: requests
Requires-Dist: pydantic
Requires-Dist: loguru
Requires-Dist: setuptools
Requires-Dist: wheel
